Workbook
Name Count: Data1!$G$1:$G$141
Name KPI_1: Data1!$H$1:$H$141
Name KPI_Name: Inputs!$I$2:$J$5
Name KPIDATA: Table1[]
Name Period: Data1!$A$1:$A$141
Name Period_List: Inputs!$G$2:$G$14
Name Position_Range: Inputs!$A$2:$A$9
Name Prod_List: Inputs!$C$2:$C$6
Name Product: Data1!$B$1:$B$141
Name Product_LUP: [1]Inputs!$M$9:$P$12
Name Sales_Per: Data1!$C$1:$C$141
Name SP_List: Inputs!$E$2:$E$7
Name Total_GP: Data1!$J$1:$J$141
Name Total_Sales: Data1!$I$1:$I$141

Sheet Dashboard1
A1: KPI In %
A2: Key Indicator | B2: Profit Margin | C2: Market Share | D2: Promotional Cost
A3: Product 1 | B3: 9 | C3: 25 | D3: 20
A4: Product 2 | B4: 20 | C4: 10 | D4: 10
A5: Product 3 | B5: 25 | C5: 5 | D5: 5
A6: Product 4 | B6: 15 | C6: 12 | D6: 25
A7: Product 5 | B7: 22 | C7: 7 | D7: 15
A11: Measurement | B11: Profit Margin | C11: Market Share | D11: Promotional Cost
A12: Red | B12: 10% and Below | C12: 10% and Below | D12: 20% And Above
A13: Orange | B13: 10% - 19% | C13: 10% - 19% | D13: 10% - 19%
A14: Green | B14: 20% and above | C14: 20% and above | D14: 10% and above

Sheet Sheet2
A1: Company | B1: KPI-1 | C1: KPI-2 | D1: KPI-3 | E1: KPI-4
A2: Comp 1 | B2: 0.38 | C2: 0.73 | D2: 0.6 | E2: 0.79
A3: Comp 2 | B3: 0.46 | C3: 0.66 | D3: 0.9 | E3: 0.29
A4: Comp 3 | B4: 0.61 | C4: 0.21 | D4: 0.47 | E4: 0.12
A5: Comp 4 | B5: 0.61 | C5: 0.21 | D5: 0.12 | E5: 0.68
A6: Comp 5 | B6: 0.78 | C6: 0.47 | D6: 0.25 | E6: 0.43
A7: Comp 6 | B7: 0.13 | C7: 0.84 | D7: 0.49 | E7: 0.53
A8: Comp 7 | B8: 0.37 | C8: 0.6 | D8: 0.31 | E8: 0.7
A9: Comp 8 | B9: 0.95 | C9: 0.93 | D9: 0.84 | E9: 0.2
A10: Comp 9 | B10: 0.49 | C10: 0.26 | D10: 0.57 | E10: 0.69
A11: Comp 10 | B11: 0.82 | C11: 0.86 | D11: 0.34 | E11: 0.61
A12: Comp 11 | B12: 0.62 | C12: 0.64 | D12: 0.87 | E12: 0.33
A13: Comp 12 | B13: 0.76 | C13: 0.24 | D13: 0.22 | E13: 0.51
... A101: Comp 100 | B101: 0.57 | C101: 0.78 | D101: 0.39 | E101: 0.12

Sheet Dashboard2
L4: S.No | M4: Name | N4: KPI 1 | O4: KPI 2 | P4: KPI 3 | Q4: KPI 4
L5: =ROWS($K$5:K5)-1+Calculation!$B$13 -> 1 | M5: =INDEX(Calculation!$Q$19:$U$118,ROWS(Dashboard2!$L$5:L5)-1+Calculation!$B$13,COLUMNS(Dashboard2!$L$5:L5)) -> Comp 3 | N5: =INDEX(Calculation!$Q$19:$U$118,ROWS(Dashboard2!$L$5:M5)-1+Calculation!$B$13,COLUMNS(Dashboard2!$L$5:M5)) -> 0.61 | O5: =INDEX(Calculation!$Q$19:$U$118,ROWS(Dashboard2!$L$5:N5)-1+Calculation!$B$13,COLUMNS(Dashboard2!$L$5:N5)) -> 0.21 | P5: =INDEX(Calculation!$Q$19:$U$118,ROWS(Dashboard2!$L$5:O5)-1+Calculation!$B$13,COLUMNS(Dashboard2!$L$5:O5)) -> 0.47 | Q5: =INDEX(Calculation!$Q$19:$U$118,ROWS(Dashboard2!$L$5:P5)-1+Calculation!$B$13,COLUMNS(Dashboard2!$L$5:P5)) -> 0.12
L6: =ROWS($K$5:K6)-1+Calculation!$B$13 -> 2 | M6: =INDEX(Calculation!$Q$19:$U$118,ROWS(Dashboard2!$L$5:L6)-1+Calculation!$B$13,COLUMNS(Dashboard2!$L$5:L6)) -> Comp 4 | N6: =INDEX(Calculation!$Q$19:$U$118,ROWS(Dashboard2!$L$5:M6)-1+Calculation!$B$13,COLUMNS(Dashboard2!$L$5:M6)) -> 0.61 | O6: =INDEX(Calculation!$Q$19:$U$118,ROWS(Dashboard2!$L$5:N6)-1+Calculation!$B$13,COLUMNS(Dashboard2!$L$5:N6)) -> 0.21 | P6: =INDEX(Calculation!$Q$19:$U$118,ROWS(Dashboard2!$L$5:O6)-1+Calculation!$B$13,COLUMNS(Dashboard2!$L$5:O6)) -> 0.12 | Q6: =INDEX(Calculation!$Q$19:$U$118,ROWS(Dashboard2!$L$5:P6)-1+Calculation!$B$13,COLUMNS(Dashboard2!$L$5:P6)) -> 0.68
L7: =ROWS($K$5:K7)-1+Calculation!$B$13 -> 3 | M7: =INDEX(Calculation!$Q$19:$U$118,ROWS(Dashboard2!$L$5:L7)-1+Calculation!$B$13,COLUMNS(Dashboard2!$L$5:L7)) -> Comp 5 | N7: =INDEX(Calculation!$Q$19:$U$118,ROWS(Dashboard2!$L$5:M7)-1+Calculation!$B$13,COLUMNS(Dashboard2!$L$5:M7)) -> 0.78 | O7: =INDEX(Calculation!$Q$19:$U$118,ROWS(Dashboard2!$L$5:N7)-1+Calculation!$B$13,COLUMNS(Dashboard2!$L$5:N7)) -> 0.47 | P7: =INDEX(Calculation!$Q$19:$U$118,ROWS(Dashboard2!$L$5:O7)-1+Calculation!$B$13,COLUMNS(Dashboard2!$L$5:O7)) -> 0.25 | Q7: =INDEX(Calculation!$Q$19:$U$118,ROWS(Dashboard2!$L$5:P7)-1+Calculation!$B$13,COLUMNS(Dashboard2!$L$5:P7)) -> 0.43
L8: =ROWS($K$5:K8)-1+Calculation!$B$13 -> 4 | M8: =INDEX(Calculation!$Q$19:$U$118,ROWS(Dashboard2!$L$5:L8)-1+Calculation!$B$13,COLUMNS(Dashboard2!$L$5:L8)) -> Comp 12 | N8: =INDEX(Calculation!$Q$19:$U$118,ROWS(Dashboard2!$L$5:M8)-1+Calculation!$B$13,COLUMNS(Dashboard2!$L$5:M8)) -> 0.76 | O8: =INDEX(Calculation!$Q$19:$U$118,ROWS(Dashboard2!$L$5:N8)-1+Calculation!$B$13,COLUMNS(Dashboard2!$L$5:N8)) -> 0.24 | P8: =INDEX(Calculation!$Q$19:$U$118,ROWS(Dashboard2!$L$5:O8)-1+Calculation!$B$13,COLUMNS(Dashboard2!$L$5:O8)) -> 0.22 | Q8: =INDEX(Calculation!$Q$19:$U$118,ROWS(Dashboard2!$L$5:P8)-1+Calculation!$B$13,COLUMNS(Dashboard2!$L$5:P8)) -> 0.51
L9: =ROWS($K$5:K9)-1+Calculation!$B$13 -> 5 | M9: =INDEX(Calculation!$Q$19:$U$118,ROWS(Dashboard2!$L$5:L9)-1+Calculation!$B$13,COLUMNS(Dashboard2!$L$5:L9)) -> Comp 14 | N9: =INDEX(Calculation!$Q$19:$U$118,ROWS(Dashboard2!$L$5:M9)-1+Calculation!$B$13,COLUMNS(Dashboard2!$L$5:M9)) -> 0.85 | O9: =INDEX(Calculation!$Q$19:$U$118,ROWS(Dashboard2!$L$5:N9)-1+Calculation!$B$13,COLUMNS(Dashboard2!$L$5:N9)) -> 0.5 | P9: =INDEX(Calculation!$Q$19:$U$118,ROWS(Dashboard2!$L$5:O9)-1+Calculation!$B$13,COLUMNS(Dashboard2!$L$5:O9)) -> 0.84 | Q9: =INDEX(Calculation!$Q$19:$U$118,ROWS(Dashboard2!$L$5:P9)-1+Calculation!$B$13,COLUMNS(Dashboard2!$L$5:P9)) -> 0.93
L10: =ROWS($K$5:K10)-1+Calculation!$B$13 -> 6 | M10: =INDEX(Calculation!$Q$19:$U$118,ROWS(Dashboard2!$L$5:L10)-1+Calculation!$B$13,COLUMNS(Dashboard2!$L$5:L10)) -> Comp 24 | N10: =INDEX(Calculation!$Q$19:$U$118,ROWS(Dashboard2!$L$5:M10)-1+Calculation!$B$13,COLUMNS(Dashboard2!$L$5:M10)) -> 0.88 | O10: =INDEX(Calculation!$Q$19:$U$118,ROWS(Dashboard2!$L$5:N10)-1+Calculation!$B$13,COLUMNS(Dashboard2!$L$5:N10)) -> 0.44 | P10: =INDEX(Calculation!$Q$19:$U$118,ROWS(Dashboard2!$L$5:O10)-1+Calculation!$B$13,COLUMNS(Dashboard2!$L$5:O10)) -> 0.89 | Q10: =INDEX(Calculation!$Q$19:$U$118,ROWS(Dashboard2!$L$5:P10)-1+Calculation!$B$13,COLUMNS(Dashboard2!$L$5:P10)) -> 0.47
L11: =ROWS($K$5:K11)-1+Calculation!$B$13 -> 7 | M11: =INDEX(Calculation!$Q$19:$U$118,ROWS(Dashboard2!$L$5:L11)-1+Calculation!$B$13,COLUMNS(Dashboard2!$L$5:L11)) -> Comp 28 | N11: =INDEX(Calculation!$Q$19:$U$118,ROWS(Dashboard2!$L$5:M11)-1+Calculation!$B$13,COLUMNS(Dashboard2!$L$5:M11)) -> 0.56 | O11: =INDEX(Calculation!$Q$19:$U$118,ROWS(Dashboard2!$L$5:N11)-1+Calculation!$B$13,COLUMNS(Dashboard2!$L$5:N11)) -> 0.27 | P11: =INDEX(Calculation!$Q$19:$U$118,ROWS(Dashboard2!$L$5:O11)-1+Calculation!$B$13,COLUMNS(Dashboard2!$L$5:O11)) -> 0.52 | Q11: =INDEX(Calculation!$Q$19:$U$118,ROWS(Dashboard2!$L$5:P11)-1+Calculation!$B$13,COLUMNS(Dashboard2!$L$5:P11)) -> 0.75
L12: =ROWS($K$5:K12)-1+Calculation!$B$13 -> 8 | M12: =INDEX(Calculation!$Q$19:$U$118,ROWS(Dashboard2!$L$5:L12)-1+Calculation!$B$13,COLUMNS(Dashboard2!$L$5:L12)) -> Comp 30 | N12: =INDEX(Calculation!$Q$19:$U$118,ROWS(Dashboard2!$L$5:M12)-1+Calculation!$B$13,COLUMNS(Dashboard2!$L$5:M12)) -> 0.61 | O12: =INDEX(Calculation!$Q$19:$U$118,ROWS(Dashboard2!$L$5:N12)-1+Calculation!$B$13,COLUMNS(Dashboard2!$L$5:N12)) -> 0.2 | P12: =INDEX(Calculation!$Q$19:$U$118,ROWS(Dashboard2!$L$5:O12)-1+Calculation!$B$13,COLUMNS(Dashboard2!$L$5:O12)) -> 0.7 | Q12: =INDEX(Calculation!$Q$19:$U$118,ROWS(Dashboard2!$L$5:P12)-1+Calculation!$B$13,COLUMNS(Dashboard2!$L$5:P12)) -> 0.77
L13: =ROWS($K$5:K13)-1+Calculation!$B$13 -> 9 | M13: =INDEX(Calculation!$Q$19:$U$118,ROWS(Dashboard2!$L$5:L13)-1+Calculation!$B$13,COLUMNS(Dashboard2!$L$5:L13)) -> Comp 35 | N13: =INDEX(Calculation!$Q$19:$U$118,ROWS(Dashboard2!$L$5:M13)-1+Calculation!$B$13,COLUMNS(Dashboard2!$L$5:M13)) -> 0.62 | O13: =INDEX(Calculation!$Q$19:$U$118,ROWS(Dashboard2!$L$5:N13)-1+Calculation!$B$13,COLUMNS(Dashboard2!$L$5:N13)) -> 0.34 | P13: =INDEX(Calculation!$Q$19:$U$118,ROWS(Dashboard2!$L$5:O13)-1+Calculation!$B$13,COLUMNS(Dashboard2!$L$5:O13)) -> 0.44 | Q13: =INDEX(Calculation!$Q$19:$U$118,ROWS(Dashboard2!$L$5:P13)-1+Calculation!$B$13,COLUMNS(Dashboard2!$L$5:P13)) -> 0.36
L14: =ROWS($K$5:K14)-1+Calculation!$B$13 -> 10 | M14: =INDEX(Calculation!$Q$19:$U$118,ROWS(Dashboard2!$L$5:L14)-1+Calculation!$B$13,COLUMNS(Dashboard2!$L$5:L14)) -> Comp 36 | N14: =INDEX(Calculation!$Q$19:$U$118,ROWS(Dashboard2!$L$5:M14)-1+Calculation!$B$13,COLUMNS(Dashboard2!$L$5:M14)) -> 0.58 | O14: =INDEX(Calculation!$Q$19:$U$118,ROWS(Dashboard2!$L$5:N14)-1+Calculation!$B$13,COLUMNS(Dashboard2!$L$5:N14)) -> 0.39 | P14: =INDEX(Calculation!$Q$19:$U$118,ROWS(Dashboard2!$L$5:O14)-1+Calculation!$B$13,COLUMNS(Dashboard2!$L$5:O14)) -> 0.45 | Q14: =INDEX(Calculation!$Q$19:$U$118,ROWS(Dashboard2!$L$5:P14)-1+Calculation!$B$13,COLUMNS(Dashboard2!$L$5:P14)) -> 0.71
H21: Comp 17

Sheet Calculation
A1: Chart Dropdown
A2: KPI-1
A3: KPI-2
A4: KPI-3
A5: KPI-4
A10: Cells Links
A11: KPI Dropdown X axis | B11: 2
A12: KPI Dropdown Y axis | B12: 1
A13: Scroll Bar | B13: 1
A14: Radio Button | B14: 2
E17: Chart Title | W17: Bullet Chart Data
A18: Chart Data | B18: X-Axis | C18: Y-Axis | E18: =INDEX($A$2:$A$5,$B$11) &" Vs, " &INDEX($A$2:$A$5,$B$12) -> KPI-2 Vs, KPI-1 | M18: Quardrant | N18: Check Quardrant | O18: Row Number | P18: Stracked Up | Q18: Company Name | R18: KPI 1 | S18: KPI 2 | T18: KPI 3 | U18: KPI 4 | W18: Company Name | X18: KPI 1 | Y18: KPI 2 | Z18: KPI 3 | AA18: KPI 4
A19: Comp 1 | B19: =INDEX(KPIDATA,ROWS($A$19:A19),$B$11+1) -> 0.73 | C19: =INDEX(KPIDATA,ROWS($A$19:A19),$B$12+1) -> 0.38 | M19: =IF(B19>0.5,IF(C19>0.5,3,5),IF(C19>0.5,2,4)) -> 5 | N19: =IF($B$14=1,TRUE,IF($B$14=M19,TRUE,FALSE)) -> FALSE | O19: =IF(N19,ROWS($N$19:N19),"") | P19: =IFERROR(SMALL($O$19:$O$118,ROWS($O$19:O19)),"") -> 3 | Q19: =IFERROR(INDEX($A$19:$A$118,P19),"") -> Comp 3 | R19: =IFERROR(INDEX(KPIDATA,MATCH(Q19,Table1[Company],0),2),"") -> 0.61 | S19: =IFERROR(INDEX(KPIDATA,MATCH(Q19,Table1[Company],0),3),"") -> 0.21 | T19: =IFERROR(INDEX(KPIDATA,MATCH(Q19,Table1[Company],0),4),"") -> 0.47 | U19: =IFERROR(INDEX(KPIDATA,MATCH(Q19,Table1[Company],0),5),"") -> 0.12 | W19: Low | X19: 0.5 | Y19: 0.5 | Z19: 0.5 | AA19: 0.5
A20: Comp 2 | B20: =INDEX(KPIDATA,ROWS($A$19:A20),$B$11+1) -> 0.66 | C20: =INDEX(KPIDATA,ROWS($A$19:A20),$B$12+1) -> 0.46 | E20: Spot the Company | M20: =IF(B20>0.5,IF(C20>0.5,3,5),IF(C20>0.5,2,4)) -> 5 | N20: =IF($B$14=1,TRUE,IF($B$14=M20,TRUE,FALSE)) -> FALSE | O20: =IF(N20,ROWS($N$19:N20),"") | P20: =IFERROR(SMALL($O$19:$O$118,ROWS($O$19:O20)),"") -> 4 | Q20: =IFERROR(INDEX($A$19:$A$118,P20),"") -> Comp 4 | R20: =IFERROR(INDEX(KPIDATA,MATCH(Q20,Table1[Company],0),2),"") -> 0.61 | S20: =IFERROR(INDEX(KPIDATA,MATCH(Q20,Table1[Company],0),3),"") -> 0.21 | T20: =IFERROR(INDEX(KPIDATA,MATCH(Q20,Table1[Company],0),4),"") -> 0.12 | U20: =IFERROR(INDEX(KPIDATA,MATCH(Q20,Table1[Company],0),5),"") -> 0.68 | W20: Medium | X20: 0.3 | Y20: 0.3 | Z20: 0.3 | AA20: 0.3
A21: Comp 3 | B21: =INDEX(KPIDATA,ROWS($A$19:A21),$B$11+1) -> 0.21 | C21: =INDEX(KPIDATA,ROWS($A$19:A21),$B$12+1) -> 0.61 | E21: =Dashboard2!H21 -> Comp 17 | F21: =VLOOKUP(E21,$A$19:$C$118,2,0) -> 0.54 | G21: =VLOOKUP(E21,$A$19:$C$118,3,0) -> 0.23 | M21: =IF(B21>0.5,IF(C21>0.5,3,5),IF(C21>0.5,2,4)) -> 2 | N21: =IF($B$14=1,TRUE,IF($B$14=M21,TRUE,FALSE)) -> TRUE | O21: =IF(N21,ROWS($N$19:N21),"") -> 3 | P21: =IFERROR(SMALL($O$19:$O$118,ROWS($O$19:O21)),"") -> 5 | Q21: =IFERROR(INDEX($A$19:$A$118,P21),"") -> Comp 5 | R21: =IFERROR(INDEX(KPIDATA,MATCH(Q21,Table1[Company],0),2),"") -> 0.78 | S21: =IFERROR(INDEX(KPIDATA,MATCH(Q21,Table1[Company],0),3),"") -> 0.47 | T21: =IFERROR(INDEX(KPIDATA,MATCH(Q21,Table1[Company],0),4),"") -> 0.25 | U21: =IFERROR(INDEX(KPIDATA,MATCH(Q21,Table1[Company],0),5),"") -> 0.43 | W21: High | X21: 0.2 | Y21: 0.2 | Z21: 0.2 | AA21: 0.2
A22: Comp 4 | B22: =INDEX(KPIDATA,ROWS($A$19:A22),$B$11+1) -> 0.21 | C22: =INDEX(KPIDATA,ROWS($A$19:A22),$B$12+1) -> 0.61 | M22: =IF(B22>0.5,IF(C22>0.5,3,5),IF(C22>0.5,2,4)) -> 2 | N22: =IF($B$14=1,TRUE,IF($B$14=M22,TRUE,FALSE)) -> TRUE | O22: =IF(N22,ROWS($N$19:N22),"") -> 4 | P22: =IFERROR(SMALL($O$19:$O$118,ROWS($O$19:O22)),"") -> 12 | Q22: =IFERROR(INDEX($A$19:$A$118,P22),"") -> Comp 12 | R22: =IFERROR(INDEX(KPIDATA,MATCH(Q22,Table1[Company],0),2),"") -> 0.76 | S22: =IFERROR(INDEX(KPIDATA,MATCH(Q22,Table1[Company],0),3),"") -> 0.24 | T22: =IFERROR(INDEX(KPIDATA,MATCH(Q22,Table1[Company],0),4),"") -> 0.22 | U22: =IFERROR(INDEX(KPIDATA,MATCH(Q22,Table1[Company],0),5),"") -> 0.51 | W22: =Dashboard2!H21 -> Comp 17 | X22: =VLOOKUP($W$22,KPIDATA,2,0) -> 0.23 | Y22: =VLOOKUP($W$22,KPIDATA,3,0) -> 0.54 | Z22: =VLOOKUP($W$22,KPIDATA,4,0) -> 0.82 | AA22: =VLOOKUP($W$22,KPIDATA,5,0) -> 0.76
A23: Comp 5 | B23: =INDEX(KPIDATA,ROWS($A$19:A23),$B$11+1) -> 0.47 | C23: =INDEX(KPIDATA,ROWS($A$19:A23),$B$12+1) -> 0.78 | E23: Quardant 1 (Bottom Left) | F23: Quardant 2 (Bottom Right) | G23: Quardant 3 (Top Right) | H23: Quardant 4 (Top Left) | J23: Dynemic Interpretation | M23: =IF(B23>0.5,IF(C23>0.5,3,5),IF(C23>0.5,2,4)) -> 2 | N23: =IF($B$14=1,TRUE,IF($B$14=M23,TRUE,FALSE)) -> TRUE | O23: =IF(N23,ROWS($N$19:N23),"") -> 5 | P23: =IFERROR(SMALL($O$19:$O$118,ROWS($O$19:O23)),"") -> 14 | Q23: =IFERROR(INDEX($A$19:$A$118,P23),"") -> Comp 14 | R23: =IFERROR(INDEX(KPIDATA,MATCH(Q23,Table1[Company],0),2),"") -> 0.85 | S23: =IFERROR(INDEX(KPIDATA,MATCH(Q23,Table1[Company],0),3),"") -> 0.5 | T23: =IFERROR(INDEX(KPIDATA,MATCH(Q23,Table1[Company],0),4),"") -> 0.84 | U23: =IFERROR(INDEX(KPIDATA,MATCH(Q23,Table1[Company],0),5),"") -> 0.93 | W23: Peer Avg | X23: =AVERAGE(Table1[KPI-1]) -> 0.5664 | Y23: =AVERAGE(Table1[KPI-2]) -> 0.5284 | Z23: =AVERAGE(Table1[KPI-3]) -> 0.5353 | AA23: =AVERAGE(Table1[KPI-4]) -> 0.5594
A24: Comp 6 | B24: =INDEX(KPIDATA,ROWS($A$19:A24),$B$11+1) -> 0.84 | C24: =INDEX(KPIDATA,ROWS($A$19:A24),$B$12+1) -> 0.13 | E24: =E21&" Lags in both the KPI's" -> Comp 17 Lags in both the KPI's | F24: =E21&" Lags its Peers in "&INDEX($A$2:$A$5,$B$12)&" however it outperforms in "&INDEX($A$2:$A$5,$B$11) -> Comp 17 Lags its Peers in KPI-1 however it outperforms in KPI-2 | J24: =IF(F21>0.5,IF(G21>0.5,G24,F24),IF(G21>0.5,H24,E24)) -> Comp 17 Lags its Peers in KPI-1 however it outperforms in KPI-2 | M24: =IF(B24>0.5,IF(C24>0.5,3,5),IF(C24>0.5,2,4)) -> 5 | N24: =IF($B$14=1,TRUE,IF($B$14=M24,TRUE,FALSE)) -> FALSE | O24: =IF(N24,ROWS($N$19:N24),"") | P24: =IFERROR(SMALL($O$19:$O$118,ROWS($O$19:O24)),"") -> 24 | Q24: =IFERROR(INDEX($A$19:$A$118,P24),"") -> Comp 24 | R24: =IFERROR(INDEX(KPIDATA,MATCH(Q24,Table1[Company],0),2),"") -> 0.88 | S24: =IFERROR(INDEX(KPIDATA,MATCH(Q24,Table1[Company],0),3),"") -> 0.44 | T24: =IFERROR(INDEX(KPIDATA,MATCH(Q24,Table1[Company],0),4),"") -> 0.89 | U24: =IFERROR(INDEX(KPIDATA,MATCH(Q24,Table1[Company],0),5),"") -> 0.47
A25: Comp 7 | B25: =INDEX(KPIDATA,ROWS($A$19:A25),$B$11+1) -> 0.6 | C25: =INDEX(KPIDATA,ROWS($A$19:A25),$B$12+1) -> 0.37 | M25: =IF(B25>0.5,IF(C25>0.5,3,5),IF(C25>0.5,2,4)) -> 5 | N25: =IF($B$14=1,TRUE,IF($B$14=M25,TRUE,FALSE)) -> FALSE | O25: =IF(N25,ROWS($N$19:N25),"") | P25: =IFERROR(SMALL($O$19:$O$118,ROWS($O$19:O25)),"") -> 28 | Q25: =IFERROR(INDEX($A$19:$A$118,P25),"") -> Comp 28 | R25: =IFERROR(INDEX(KPIDATA,MATCH(Q25,Table1[Company],0),2),"") -> 0.56 | S25: =IFERROR(INDEX(KPIDATA,MATCH(Q25,Table1[Company],0),3),"") -> 0.27 | T25: =IFERROR(INDEX(KPIDATA,MATCH(Q25,Table1[Company],0),4),"") -> 0.52 | U25: =IFERROR(INDEX(KPIDATA,MATCH(Q25,Table1[Company],0),5),"") -> 0.75
A26: Comp 8 | B26: =INDEX(KPIDATA,ROWS($A$19:A26),$B$11+1) -> 0.93 | C26: =INDEX(KPIDATA,ROWS($A$19:A26),$B$12+1) -> 0.95 | M26: =IF(B26>0.5,IF(C26>0.5,3,5),IF(C26>0.5,2,4)) -> 3 | N26: =IF($B$14=1,TRUE,IF($B$14=M26,TRUE,FALSE)) -> FALSE | O26: =IF(N26,ROWS($N$19:N26),"") | P26: =IFERROR(SMALL($O$19:$O$118,ROWS($O$19:O26)),"") -> 30 | Q26: =IFERROR(INDEX($A$19:$A$118,P26),"") -> Comp 30 | R26: =IFERROR(INDEX(KPIDATA,MATCH(Q26,Table1[Company],0),2),"") -> 0.61 | S26: =IFERROR(INDEX(KPIDATA,MATCH(Q26,Table1[Company],0),3),"") -> 0.2 | T26: =IFERROR(INDEX(KPIDATA,MATCH(Q26,Table1[Company],0),4),"") -> 0.7 | U26: =IFERROR(INDEX(KPIDATA,MATCH(Q26,Table1[Company],0),5),"") -> 0.77
A27: Comp 9 | B27: =INDEX(KPIDATA,ROWS($A$19:A27),$B$11+1) -> 0.26 | C27: =INDEX(KPIDATA,ROWS($A$19:A27),$B$12+1) -> 0.49 | M27: =IF(B27>0.5,IF(C27>0.5,3,5),IF(C27>0.5,2,4)) -> 4 | N27: =IF($B$14=1,TRUE,IF($B$14=M27,TRUE,FALSE)) -> FALSE | O27: =IF(N27,ROWS($N$19:N27),"") | P27: =IFERROR(SMALL($O$19:$O$118,ROWS($O$19:O27)),"") -> 35 | Q27: =IFERROR(INDEX($A$19:$A$118,P27),"") -> Comp 35 | R27: =IFERROR(INDEX(KPIDATA,MATCH(Q27,Table1[Company],0),2),"") -> 0.62 | S27: =IFERROR(INDEX(KPIDATA,MATCH(Q27,Table1[Company],0),3),"") -> 0.34 | T27: =IFERROR(INDEX(KPIDATA,MATCH(Q27,Table1[Company],0),4),"") -> 0.44 | U27: =IFERROR(INDEX(KPIDATA,MATCH(Q27,Table1[Company],0),5),"") -> 0.36
A28: Comp 10 | B28: =INDEX(KPIDATA,ROWS($A$19:A28),$B$11+1) -> 0.86 | C28: =INDEX(KPIDATA,ROWS($A$19:A28),$B$12+1) -> 0.82 | M28: =IF(B28>0.5,IF(C28>0.5,3,5),IF(C28>0.5,2,4)) -> 3 | N28: =IF($B$14=1,TRUE,IF($B$14=M28,TRUE,FALSE)) -> FALSE | O28: =IF(N28,ROWS($N$19:N28),"") | P28: =IFERROR(SMALL($O$19:$O$118,ROWS($O$19:O28)),"") -> 36 | Q28: =IFERROR(INDEX($A$19:$A$118,P28),"") -> Comp 36 | R28: =IFERROR(INDEX(KPIDATA,MATCH(Q28,Table1[Company],0),2),"") -> 0.58 | S28: =IFERROR(INDEX(KPIDATA,MATCH(Q28,Table1[Company],0),3),"") -> 0.39 | T28: =IFERROR(INDEX(KPIDATA,MATCH(Q28,Table1[Company],0),4),"") -> 0.45 | U28: =IFERROR(INDEX(KPIDATA,MATCH(Q28,Table1[Company],0),5),"") -> 0.71
A29: Comp 11 | B29: =INDEX(KPIDATA,ROWS($A$19:A29),$B$11+1) -> 0.64 | C29: =INDEX(KPIDATA,ROWS($A$19:A29),$B$12+1) -> 0.62 | M29: =IF(B29>0.5,IF(C29>0.5,3,5),IF(C29>0.5,2,4)) -> 3 | N29: =IF($B$14=1,TRUE,IF($B$14=M29,TRUE,FALSE)) -> FALSE | O29: =IF(N29,ROWS($N$19:N29),"") | P29: =IFERROR(SMALL($O$19:$O$118,ROWS($O$19:O29)),"") -> 42 | Q29: =IFERROR(INDEX($A$19:$A$118,P29),"") -> Comp 42 | R29: =IFERROR(INDEX(KPIDATA,MATCH(Q29,Table1[Company],0),2),"") -> 0.94 | S29: =IFERROR(INDEX(KPIDATA,MATCH(Q29,Table1[Company],0),3),"") -> 0.2 | T29: =IFERROR(INDEX(KPIDATA,MATCH(Q29,Table1[Company],0),4),"") -> 0.18 | U29: =IFERROR(INDEX(KPIDATA,MATCH(Q29,Table1[Company],0),5),"") -> 0.94
A30: Comp 12 | B30: =INDEX(KPIDATA,ROWS($A$19:A30),$B$11+1) -> 0.24 | C30: =INDEX(KPIDATA,ROWS($A$19:A30),$B$12+1) -> 0.76 | M30: =IF(B30>0.5,IF(C30>0.5,3,5),IF(C30>0.5,2,4)) -> 2 | N30: =IF($B$14=1,TRUE,IF($B$14=M30,TRUE,FALSE)) -> TRUE | O30: =IF(N30,ROWS($N$19:N30),"") -> 12 | P30: =IFERROR(SMALL($O$19:$O$118,ROWS($O$19:O30)),"") -> 46 | Q30: =IFERROR(INDEX($A$19:$A$118,P30),"") -> Comp 46 | R30: =IFERROR(INDEX(KPIDATA,MATCH(Q30,Table1[Company],0),2),"") -> 0.84 | S30: =IFERROR(INDEX(KPIDATA,MATCH(Q30,Table1[Company],0),3),"") -> 0.21 | T30: =IFERROR(INDEX(KPIDATA,MATCH(Q30,Table1[Company],0),4),"") -> 0.74 | U30: =IFERROR(INDEX(KPIDATA,MATCH(Q30,Table1[Company],0),5),"") -> 0.69
A31: Comp 13 | B31: =INDEX(KPIDATA,ROWS($A$19:A31),$B$11+1) -> 0.52 | C31: =INDEX(KPIDATA,ROWS($A$19:A31),$B$12+1) -> 0.35 | M31: =IF(B31>0.5,IF(C31>0.5,3,5),IF(C31>0.5,2,4)) -> 5 | N31: =IF($B$14=1,TRUE,IF($B$14=M31,TRUE,FALSE)) -> FALSE | O31: =IF(N31,ROWS($N$19:N31),"") | P31: =IFERROR(SMALL($O$19:$O$118,ROWS($O$19:O31)),"") -> 47 | Q31: =IFERROR(INDEX($A$19:$A$118,P31),"") -> Comp 47 | R31: =IFERROR(INDEX(KPIDATA,MATCH(Q31,Table1[Company],0),2),"") -> 0.82 | S31: =IFERROR(INDEX(KPIDATA,MATCH(Q31,Table1[Company],0),3),"") -> 0.44 | T31: =IFERROR(INDEX(KPIDATA,MATCH(Q31,Table1[Company],0),4),"") -> 0.95 | U31: =IFERROR(INDEX(KPIDATA,MATCH(Q31,Table1[Company],0),5),"") -> 0.79
A32: Comp 14 | B32: =INDEX(KPIDATA,ROWS($A$19:A32),$B$11+1) -> 0.5 | C32: =INDEX(KPIDATA,ROWS($A$19:A32),$B$12+1) -> 0.85 | M32: =IF(B32>0.5,IF(C32>0.5,3,5),IF(C32>0.5,2,4)) -> 2 | N32: =IF($B$14=1,TRUE,IF($B$14=M32,TRUE,FALSE)) -> TRUE | O32: =IF(N32,ROWS($N$19:N32),"") -> 14 | P32: =IFERROR(SMALL($O$19:$O$118,ROWS($O$19:O32)),"") -> 48 | Q32: =IFERROR(INDEX($A$19:$A$118,P32),"") -> Comp 48 | R32: =IFERROR(INDEX(KPIDATA,MATCH(Q32,Table1[Company],0),2),"") -> 0.74 | S32: =IFERROR(INDEX(KPIDATA,MATCH(Q32,Table1[Company],0),3),"") -> 0.37 | T32: =IFERROR(INDEX(KPIDATA,MATCH(Q32,Table1[Company],0),4),"") -> 0.75 | U32: =IFERROR(INDEX(KPIDATA,MATCH(Q32,Table1[Company],0),5),"") -> 0.12
A33: Comp 15 | B33: =INDEX(KPIDATA,ROWS($A$19:A33),$B$11+1) -> 0.83 | C33: =INDEX(KPIDATA,ROWS($A$19:A33),$B$12+1) -> 0.92 | M33: =IF(B33>0.5,IF(C33>0.5,3,5),IF(C33>0.5,2,4)) -> 3 | N33: =IF($B$14=1,TRUE,IF($B$14=M33,TRUE,FALSE)) -> FALSE | O33: =IF(N33,ROWS($N$19:N33),"") | P33: =IFERROR(SMALL($O$19:$O$118,ROWS($O$19:O33)),"") -> 49 | Q33: =IFERROR(INDEX($A$19:$A$118,P33),"") -> Comp 49 | R33: =IFERROR(INDEX(KPIDATA,MATCH(Q33,Table1[Company],0),2),"") -> 0.82 | S33: =IFERROR(INDEX(KPIDATA,MATCH(Q33,Table1[Company],0),3),"") -> 0.18 | T33: =IFERROR(INDEX(KPIDATA,MATCH(Q33,Table1[Company],0),4),"") -> 0.94 | U33: =IFERROR(INDEX(KPIDATA,MATCH(Q33,Table1[Company],0),5),"") -> 0.68
A34: Comp 16 | B34: =INDEX(KPIDATA,ROWS($A$19:A34),$B$11+1) -> 0.78 | C34: =INDEX(KPIDATA,ROWS($A$19:A34),$B$12+1) -> 0.95 | M34: =IF(B34>0.5,IF(C34>0.5,3,5),IF(C34>0.5,2,4)) -> 3 | N34: =IF($B$14=1,TRUE,IF($B$14=M34,TRUE,FALSE)) -> FALSE | O34: =IF(N34,ROWS($N$19:N34),"") | P34: =IFERROR(SMALL($O$19:$O$118,ROWS($O$19:O34)),"") -> 54 | Q34: =IFERROR(INDEX($A$19:$A$118,P34),"") -> Comp 54 | R34: =IFERROR(INDEX(KPIDATA,MATCH(Q34,Table1[Company],0),2),"") -> 0.75 | S34: =IFERROR(INDEX(KPIDATA,MATCH(Q34,Table1[Company],0),3),"") -> 0.4 | T34: =IFERROR(INDEX(KPIDATA,MATCH(Q34,Table1[Company],0),4),"") -> 0.66 | U34: =IFERROR(INDEX(KPIDATA,MATCH(Q34,Table1[Company],0),5),"") -> 0.2
A35: Comp 17 | B35: =INDEX(KPIDATA,ROWS($A$19:A35),$B$11+1) -> 0.54 | C35: =INDEX(KPIDATA,ROWS($A$19:A35),$B$12+1) -> 0.23 | M35: =IF(B35>0.5,IF(C35>0.5,3,5),IF(C35>0.5,2,4)) -> 5 | N35: =IF($B$14=1,TRUE,IF($B$14=M35,TRUE,FALSE)) -> FALSE | O35: =IF(N35,ROWS($N$19:N35),"") | P35: =IFERROR(SMALL($O$19:$O$118,ROWS($O$19:O35)),"") -> 66 | Q35: =IFERROR(INDEX($A$19:$A$118,P35),"") -> Comp 66 | R35: =IFERROR(INDEX(KPIDATA,MATCH(Q35,Table1[Company],0),2),"") -> 0.73 | S35: =IFERROR(INDEX(KPIDATA,MATCH(Q35,Table1[Company],0),3),"") -> 0.17 | T35: =IFERROR(INDEX(KPIDATA,MATCH(Q35,Table1[Company],0),4),"") -> 0.96 | U35: =IFERROR(INDEX(KPIDATA,MATCH(Q35,Table1[Company],0),5),"") -> 0.41
A36: Comp 18 | B36: =INDEX(KPIDATA,ROWS($A$19:A36),$B$11+1) -> 0.25 | C36: =INDEX(KPIDATA,ROWS($A$19:A36),$B$12+1) -> 0.22 | M36: =IF(B36>0.5,IF(C36>0.5,3,5),IF(C36>0.5,2,4)) -> 4 | N36: =IF($B$14=1,TRUE,IF($B$14=M36,TRUE,FALSE)) -> FALSE | O36: =IF(N36,ROWS($N$19:N36),"") | P36: =IFERROR(SMALL($O$19:$O$118,ROWS($O$19:O36)),"") -> 70 | Q36: =IFERROR(INDEX($A$19:$A$118,P36),"") -> Comp 70 | R36: =IFERROR(INDEX(KPIDATA,MATCH(Q36,Table1[Company],0),2),"") -> 0.57 | S36: =IFERROR(INDEX(KPIDATA,MATCH(Q36,Table1[Company],0),3),"") -> 0.49 | T36: =IFERROR(INDEX(KPIDATA,MATCH(Q36,Table1[Company],0),4),"") -> 0.25 | U36: =IFERROR(INDEX(KPIDATA,MATCH(Q36,Table1[Company],0),5),"") -> 0.77
... A118: Comp 100 | B118: =INDEX(KPIDATA,ROWS($A$19:A118),$B$11+1) -> 0.78 | C118: =INDEX(KPIDATA,ROWS($A$19:A118),$B$12+1) -> 0.57 | M118: =IF(B118>0.5,IF(C118>0.5,3,5),IF(C118>0.5,2,4)) -> 3 | N118: =IF($B$14=1,TRUE,IF($B$14=M118,TRUE,FALSE)) -> FALSE | O118: =IF(N118,ROWS($N$19:N118),"") | P118: =IFERROR(SMALL($O$19:$O$118,ROWS($O$19:O118)),"") | Q118: =IFERROR(INDEX($A$19:$A$118,P118),"") | R118: =IFERROR(INDEX(KPIDATA,MATCH(Q118,Table1[Company],0),2),"") | S118: =IFERROR(INDEX(KPIDATA,MATCH(Q118,Table1[Company],0),3),"") | T118: =IFERROR(INDEX(KPIDATA,MATCH(Q118,Table1[Company],0),4),"") | U118: =IFERROR(INDEX(KPIDATA,MATCH(Q118,Table1[Company],0),5),"")

Sheet Dashboard3
A1: Item | B1: Sales | C1: Week | O1: Curd
A2: Curd | B2: 100 | C2: Week1 | O2: Milk
A3: Milk | B3: 222 | C3: Week1 | F3: Milk | G3: ="Count of Item"&" "&F3&" is--> "&COUNTIF(A:A,F3) -> Count of Item Milk is--> 1 | O3: Maggie
A4: Maggie | B4: 344 | C4: Week2 | F4: Week3 | G4: ="Total Item Sold for"&" "& F4 &" is "&SUMIFS(B:B,A:A,$F$3,C:C,F4) -> Total Item Sold for Week3 is 0 | O4: Pulses
A5: Pulses | B5: 456 | C5: Week2 | O5: Papaya
A6: Papaya | B6: 588 | C6: Week2 | O6: Gauva
A7: Gauva | B7: 710 | C7: Week2
A8: Curd | B8: 832 | C8: Week2
A9: Curd | B9: 41 | C9: Week2
A10: Pulses | B10: 3 | C10: Week2
A11: Pulses | B11: 5 | C11: Week1
A12: Pulses | B12: 6 | C12: Week1
A13: Gauva | B13: 76 | C13: Week1
A14: Maggie | B14: 32 | C14: Week1
A15: Pulses | B15: 55 | C15: Week3
A16: Papaya | B16: 22 | C16: Week3
A17: Maggie | B17: 78 | C17: Week3
A18: Pulses | B18: 7 | C18: Week3
... A21: Papaya | B21: 224 | C21: Week1

Sheet Data
A1: Client Name | B1: Industry | C1: Country | D1: Date of Win | E1: Win Value | H1: H1 | I1: H2 | J1: H3 | K1: H4 | L1: Cal-1 | M1: Cal-2
A2: Client 1 | B2: Healthcare | C2: China | D2: 41671 | E2: 239 | H2: =IF(Dashboard4!$S$2="All Industry",TRUE,Dashboard4!$S$2=Data!B2:B100) -> TRUE | I2: =IF(Dashboard4!$T$2="All Country",TRUE,Dashboard4!$T$2=Data!C2:C100) -> TRUE | J2: =IF(Dashboard4!$U$2="All Months",TRUE,Dashboard4!$U$1=MONTH(Data!D2)) -> FALSE | K2: =AND(H2:J2) -> FALSE | L2: =IF(K2,ROWS($K$2:K2),"") | M2: =IFERROR(SMALL($L$2:$L$45,ROWS($L$2:L2)),"") -> 29
A3: Client 2 | B3: Banking | C3: Franch | D3: 41791 | E3: 530 | H3: =IF(Dashboard4!$S$2="All Industry",TRUE,Dashboard4!$S$2=Data!B3:B101) -> TRUE | I3: =IF(Dashboard4!$T$2="All Country",TRUE,Dashboard4!$T$2=Data!C3:C101) -> TRUE | J3: =IF(Dashboard4!$U$2="All Months",TRUE,Dashboard4!$U$1=MONTH(Data!D3)) -> FALSE | K3: =AND(H3:J3) -> FALSE | L3: =IF(K3,ROWS($K$2:K3),"") | M3: =IFERROR(SMALL($L$2:$L$45,ROWS($L$2:L3)),"") -> 30
A4: Client 3 | B4: Advertisment | C4: US | D4: 41852 | E4: 632 | H4: =IF(Dashboard4!$S$2="All Industry",TRUE,Dashboard4!$S$2=Data!B4:B102) -> TRUE | I4: =IF(Dashboard4!$T$2="All Country",TRUE,Dashboard4!$T$2=Data!C4:C102) -> TRUE | J4: =IF(Dashboard4!$U$2="All Months",TRUE,Dashboard4!$U$1=MONTH(Data!D4)) -> FALSE | K4: =AND(H4:J4) -> FALSE | L4: =IF(K4,ROWS($K$2:K4),"") | M4: =IFERROR(SMALL($L$2:$L$45,ROWS($L$2:L4)),"") -> 31
A5: Client 4 | B5: IT | C5: Spain | D5: 41673 | E5: 941 | H5: =IF(Dashboard4!$S$2="All Industry",TRUE,Dashboard4!$S$2=Data!B5:B103) -> TRUE | I5: =IF(Dashboard4!$T$2="All Country",TRUE,Dashboard4!$T$2=Data!C5:C103) -> TRUE | J5: =IF(Dashboard4!$U$2="All Months",TRUE,Dashboard4!$U$1=MONTH(Data!D5)) -> FALSE | K5: =AND(H5:J5) -> FALSE | L5: =IF(K5,ROWS($K$2:K5),"") | M5: =IFERROR(SMALL($L$2:$L$45,ROWS($L$2:L5)),"") -> 32
A6: Client 5 | B6: Retail | C6: Germany | D6: 41673 | E6: 389 | H6: =IF(Dashboard4!$S$2="All Industry",TRUE,Dashboard4!$S$2=Data!B6:B104) -> TRUE | I6: =IF(Dashboard4!$T$2="All Country",TRUE,Dashboard4!$T$2=Data!C6:C104) -> TRUE | J6: =IF(Dashboard4!$U$2="All Months",TRUE,Dashboard4!$U$1=MONTH(Data!D6)) -> FALSE | K6: =AND(H6:J6) -> FALSE | L6: =IF(K6,ROWS($K$2:K6),"") | M6: =IFERROR(SMALL($L$2:$L$45,ROWS($L$2:L6)),"") -> 33
A7: Client 6 | B7: Accounting | C7: Canada | D7: 41673 | E7: 982 | H7: =IF(Dashboard4!$S$2="All Industry",TRUE,Dashboard4!$S$2=Data!B7:B105) -> TRUE | I7: =IF(Dashboard4!$T$2="All Country",TRUE,Dashboard4!$T$2=Data!C7:C105) -> TRUE | J7: =IF(Dashboard4!$U$2="All Months",TRUE,Dashboard4!$U$1=MONTH(Data!D7)) -> FALSE | K7: =AND(H7:J7) -> FALSE | L7: =IF(K7,ROWS($K$2:K7),"") | M7: =IFERROR(SMALL($L$2:$L$45,ROWS($L$2:L7)),"")
A8: Client 7 | B8: Retail | C8: Franch | D8: 41673 | E8: 680 | H8: =IF(Dashboard4!$S$2="All Industry",TRUE,Dashboard4!$S$2=Data!B8:B106) -> TRUE | I8: =IF(Dashboard4!$T$2="All Country",TRUE,Dashboard4!$T$2=Data!C8:C106) -> TRUE | J8: =IF(Dashboard4!$U$2="All Months",TRUE,Dashboard4!$U$1=MONTH(Data!D8)) -> FALSE | K8: =AND(H8:J8) -> FALSE | L8: =IF(K8,ROWS($K$2:K8),"") | M8: =IFERROR(SMALL($L$2:$L$45,ROWS($L$2:L8)),"")
A9: Client 8 | B9: Banking | C9: US | D9: 41673 | E9: 717 | H9: =IF(Dashboard4!$S$2="All Industry",TRUE,Dashboard4!$S$2=Data!B9:B107) -> TRUE | I9: =IF(Dashboard4!$T$2="All Country",TRUE,Dashboard4!$T$2=Data!C9:C107) -> TRUE | J9: =IF(Dashboard4!$U$2="All Months",TRUE,Dashboard4!$U$1=MONTH(Data!D9)) -> FALSE | K9: =AND(H9:J9) -> FALSE | L9: =IF(K9,ROWS($K$2:K9),"") | M9: =IFERROR(SMALL($L$2:$L$45,ROWS($L$2:L9)),"")
A10: Client 9 | B10: Retail | C10: Spain | D10: 41673 | E10: 226 | H10: =IF(Dashboard4!$S$2="All Industry",TRUE,Dashboard4!$S$2=Data!B10:B108) -> TRUE | I10: =IF(Dashboard4!$T$2="All Country",TRUE,Dashboard4!$T$2=Data!C10:C108) -> TRUE | J10: =IF(Dashboard4!$U$2="All Months",TRUE,Dashboard4!$U$1=MONTH(Data!D10)) -> FALSE | K10: =AND(H10:J10) -> FALSE | L10: =IF(K10,ROWS($K$2:K10),"") | M10: =IFERROR(SMALL($L$2:$L$45,ROWS($L$2:L10)),"")
A11: Client 10 | B11: Healthcare | C11: China | D11: 41654 | E11: 738 | H11: =IF(Dashboard4!$S$2="All Industry",TRUE,Dashboard4!$S$2=Data!B11:B109) -> TRUE | I11: =IF(Dashboard4!$T$2="All Country",TRUE,Dashboard4!$T$2=Data!C11:C109) -> TRUE | J11: =IF(Dashboard4!$U$2="All Months",TRUE,Dashboard4!$U$1=MONTH(Data!D11)) -> FALSE | K11: =AND(H11:J11) -> FALSE | L11: =IF(K11,ROWS($K$2:K11),"") | M11: =IFERROR(SMALL($L$2:$L$45,ROWS($L$2:L11)),"")
A12: Client 11 | B12: IT | C12: China | D12: 41654 | E12: 107 | H12: =IF(Dashboard4!$S$2="All Industry",TRUE,Dashboard4!$S$2=Data!B12:B110) -> TRUE | I12: =IF(Dashboard4!$T$2="All Country",TRUE,Dashboard4!$T$2=Data!C12:C110) -> TRUE | J12: =IF(Dashboard4!$U$2="All Months",TRUE,Dashboard4!$U$1=MONTH(Data!D12)) -> FALSE | K12: =AND(H12:J12) -> FALSE | L12: =IF(K12,ROWS($K$2:K12),"") | M12: =IFERROR(SMALL($L$2:$L$45,ROWS($L$2:L12)),"")
A13: Client 12 | B13: Banking | C13: Franch | D13: 41654 | E13: 965 | H13: =IF(Dashboard4!$S$2="All Industry",TRUE,Dashboard4!$S$2=Data!B13:B111) -> TRUE | I13: =IF(Dashboard4!$T$2="All Country",TRUE,Dashboard4!$T$2=Data!C13:C111) -> TRUE | J13: =IF(Dashboard4!$U$2="All Months",TRUE,Dashboard4!$U$1=MONTH(Data!D13)) -> FALSE | K13: =AND(H13:J13) -> FALSE | L13: =IF(K13,ROWS($K$2:K13),"") | M13: =IFERROR(SMALL($L$2:$L$45,ROWS($L$2:L13)),"")
... A100: Client 99 | B100: Healthcare | C100: China | D100: 41730 | E100: 678 | H100: =IF(Dashboard4!$S$2="All Industry",TRUE,Dashboard4!$S$2=Data!B100:B198) -> TRUE | I100: =IF(Dashboard4!$T$2="All Country",TRUE,Dashboard4!$T$2=Data!C100:C198) -> TRUE | J100: =IF(Dashboard4!$U$2="All Months",TRUE,Dashboard4!$U$1=MONTH(Data!D100)) -> FALSE | K100: =AND(H100:J100) -> FALSE | L100: =IF(K100,ROWS($K$2:K100),"") | M100: =IFERROR(SMALL($L$2:$L$45,ROWS($L$2:L100)),"")

Sheet Dashboard4
O1: All Industry | P1: All Country | Q1: All Months | S1: 1 | T1: 1 | U1: 12
O2: Healthcare | P2: China | Q2: Jan | S2: =INDEX($O$1:$O$7,S1) -> All Industry | T2: =INDEX($P$1:$P$7,T1) -> All Country | U2: =INDEX($Q$2:$Q$13,U1) -> Dec
O3: Banking | P3: Franch | Q3: Feb
O4: Advertisment | P4: US | Q4: Mar
B5: Client Name | C5: Industry | D5: Country | E5: Date of Win | F5: Win Value | O5: IT | P5: Spain | Q5: Apr
B6: =IFERROR(INDEX(Data!$A$2:$E$45,Data!$M2,COLUMNS(Data!$F$1:F1)),"") -> Client 29 | C6: =IFERROR(INDEX(Data!$A$2:$E$45,Data!$M2,COLUMNS(Data!$F$1:G1)),"") -> Banking | D6: =IFERROR(INDEX(Data!$A$2:$E$45,Data!$M2,COLUMNS(Data!$F$1:H1)),"") -> Canada | E6: =IFERROR(INDEX(Data!$A$2:$E$45,Data!$M2,COLUMNS(Data!$F$1:I1)),"") -> 41974 | F6: =IFERROR(INDEX(Data!$A$2:$E$45,Data!$M2,COLUMNS(Data!$F$1:J1)),"") -> 581 | O6: Retail | P6: Germany | Q6: May | S6: =COUNTIF($B$6:$B$59,"?*") -> 5
B7: =IFERROR(INDEX(Data!$A$2:$E$45,Data!$M3,COLUMNS(Data!$F$1:F2)),"") -> Client 30 | C7: =IFERROR(INDEX(Data!$A$2:$E$45,Data!$M3,COLUMNS(Data!$F$1:G2)),"") -> Healthcare | D7: =IFERROR(INDEX(Data!$A$2:$E$45,Data!$M3,COLUMNS(Data!$F$1:H2)),"") -> Canada | E7: =IFERROR(INDEX(Data!$A$2:$E$45,Data!$M3,COLUMNS(Data!$F$1:I2)),"") -> 41974 | F7: =IFERROR(INDEX(Data!$A$2:$E$45,Data!$M3,COLUMNS(Data!$F$1:J2)),"") -> 415 | O7: Accounting | P7: Canada | Q7: Jun | S7: =SUM(F6:F69) -> 2250
B8: =IFERROR(INDEX(Data!$A$2:$E$45,Data!$M4,COLUMNS(Data!$F$1:F3)),"") -> Client 31 | C8: =IFERROR(INDEX(Data!$A$2:$E$45,Data!$M4,COLUMNS(Data!$F$1:G3)),"") -> Healthcare | D8: =IFERROR(INDEX(Data!$A$2:$E$45,Data!$M4,COLUMNS(Data!$F$1:H3)),"") -> Germany | E8: =IFERROR(INDEX(Data!$A$2:$E$45,Data!$M4,COLUMNS(Data!$F$1:I3)),"") -> 41974 | F8: =IFERROR(INDEX(Data!$A$2:$E$45,Data!$M4,COLUMNS(Data!$F$1:J3)),"") -> 815 | Q8: Jul
B9: =IFERROR(INDEX(Data!$A$2:$E$45,Data!$M5,COLUMNS(Data!$F$1:F4)),"") -> Client 32 | C9: =IFERROR(INDEX(Data!$A$2:$E$45,Data!$M5,COLUMNS(Data!$F$1:G4)),"") -> Advertisment | D9: =IFERROR(INDEX(Data!$A$2:$E$45,Data!$M5,COLUMNS(Data!$F$1:H4)),"") -> US | E9: =IFERROR(INDEX(Data!$A$2:$E$45,Data!$M5,COLUMNS(Data!$F$1:I4)),"") -> 41974 | F9: =IFERROR(INDEX(Data!$A$2:$E$45,Data!$M5,COLUMNS(Data!$F$1:J4)),"") -> 213 | Q9: Aug
B10: =IFERROR(INDEX(Data!$A$2:$E$45,Data!$M6,COLUMNS(Data!$F$1:F5)),"") -> Client 33 | C10: =IFERROR(INDEX(Data!$A$2:$E$45,Data!$M6,COLUMNS(Data!$F$1:G5)),"") -> Accounting | D10: =IFERROR(INDEX(Data!$A$2:$E$45,Data!$M6,COLUMNS(Data!$F$1:H5)),"") -> China | E10: =IFERROR(INDEX(Data!$A$2:$E$45,Data!$M6,COLUMNS(Data!$F$1:I5)),"") -> 41974 | F10: =IFERROR(INDEX(Data!$A$2:$E$45,Data!$M6,COLUMNS(Data!$F$1:J5)),"") -> 226 | Q10: Sep
B11: =IFERROR(INDEX(Data!$A$2:$E$45,Data!$M7,COLUMNS(Data!$F$1:F6)),"") | C11: =IFERROR(INDEX(Data!$A$2:$E$45,Data!$M7,COLUMNS(Data!$F$1:G6)),"") | D11: =IFERROR(INDEX(Data!$A$2:$E$45,Data!$M7,COLUMNS(Data!$F$1:H6)),"") | E11: =IFERROR(INDEX(Data!$A$2:$E$45,Data!$M7,COLUMNS(Data!$F$1:I6)),"") | F11: =IFERROR(INDEX(Data!$A$2:$E$45,Data!$M7,COLUMNS(Data!$F$1:J6)),"") | Q11: Oct
B12: =IFERROR(INDEX(Data!$A$2:$E$45,Data!$M8,COLUMNS(Data!$F$1:F7)),"") | C12: =IFERROR(INDEX(Data!$A$2:$E$45,Data!$M8,COLUMNS(Data!$F$1:G7)),"") | D12: =IFERROR(INDEX(Data!$A$2:$E$45,Data!$M8,COLUMNS(Data!$F$1:H7)),"") | E12: =IFERROR(INDEX(Data!$A$2:$E$45,Data!$M8,COLUMNS(Data!$F$1:I7)),"") | F12: =IFERROR(INDEX(Data!$A$2:$E$45,Data!$M8,COLUMNS(Data!$F$1:J7)),"") | Q12: Nov
B13: =IFERROR(INDEX(Data!$A$2:$E$45,Data!$M9,COLUMNS(Data!$F$1:F8)),"") | C13: =IFERROR(INDEX(Data!$A$2:$E$45,Data!$M9,COLUMNS(Data!$F$1:G8)),"") | D13: =IFERROR(INDEX(Data!$A$2:$E$45,Data!$M9,COLUMNS(Data!$F$1:H8)),"") | E13: =IFERROR(INDEX(Data!$A$2:$E$45,Data!$M9,COLUMNS(Data!$F$1:I8)),"") | F13: =IFERROR(INDEX(Data!$A$2:$E$45,Data!$M9,COLUMNS(Data!$F$1:J8)),"") | Q13: Dec
B14: =IFERROR(INDEX(Data!$A$2:$E$45,Data!$M10,COLUMNS(Data!$F$1:F9)),"") | C14: =IFERROR(INDEX(Data!$A$2:$E$45,Data!$M10,COLUMNS(Data!$F$1:G9)),"") | D14: =IFERROR(INDEX(Data!$A$2:$E$45,Data!$M10,COLUMNS(Data!$F$1:H9)),"") | E14: =IFERROR(INDEX(Data!$A$2:$E$45,Data!$M10,COLUMNS(Data!$F$1:I9)),"") | F14: =IFERROR(INDEX(Data!$A$2:$E$45,Data!$M10,COLUMNS(Data!$F$1:J9)),"")
B15: =IFERROR(INDEX(Data!$A$2:$E$45,Data!$M11,COLUMNS(Data!$F$1:F10)),"") | C15: =IFERROR(INDEX(Data!$A$2:$E$45,Data!$M11,COLUMNS(Data!$F$1:G10)),"") | D15: =IFERROR(INDEX(Data!$A$2:$E$45,Data!$M11,COLUMNS(Data!$F$1:H10)),"") | E15: =IFERROR(INDEX(Data!$A$2:$E$45,Data!$M11,COLUMNS(Data!$F$1:I10)),"") | F15: =IFERROR(INDEX(Data!$A$2:$E$45,Data!$M11,COLUMNS(Data!$F$1:J10)),"")
B16: =IFERROR(INDEX(Data!$A$2:$E$45,Data!$M12,COLUMNS(Data!$F$1:F11)),"") | C16: =IFERROR(INDEX(Data!$A$2:$E$45,Data!$M12,COLUMNS(Data!$F$1:G11)),"") | D16: =IFERROR(INDEX(Data!$A$2:$E$45,Data!$M12,COLUMNS(Data!$F$1:H11)),"") | E16: =IFERROR(INDEX(Data!$A$2:$E$45,Data!$M12,COLUMNS(Data!$F$1:I11)),"") | F16: =IFERROR(INDEX(Data!$A$2:$E$45,Data!$M12,COLUMNS(Data!$F$1:J11)),"")
B17: =IFERROR(INDEX(Data!$A$2:$E$45,Data!$M13,COLUMNS(Data!$F$1:F12)),"") | C17: =IFERROR(INDEX(Data!$A$2:$E$45,Data!$M13,COLUMNS(Data!$F$1:G12)),"") | D17: =IFERROR(INDEX(Data!$A$2:$E$45,Data!$M13,COLUMNS(Data!$F$1:H12)),"") | E17: =IFERROR(INDEX(Data!$A$2:$E$45,Data!$M13,COLUMNS(Data!$F$1:I12)),"") | F17: =IFERROR(INDEX(Data!$A$2:$E$45,Data!$M13,COLUMNS(Data!$F$1:J12)),"")
B18: =IFERROR(INDEX(Data!$A$2:$E$45,Data!$M14,COLUMNS(Data!$F$1:F13)),"") | C18: =IFERROR(INDEX(Data!$A$2:$E$45,Data!$M14,COLUMNS(Data!$F$1:G13)),"") | D18: =IFERROR(INDEX(Data!$A$2:$E$45,Data!$M14,COLUMNS(Data!$F$1:H13)),"") | E18: =IFERROR(INDEX(Data!$A$2:$E$45,Data!$M14,COLUMNS(Data!$F$1:I13)),"") | F18: =IFERROR(INDEX(Data!$A$2:$E$45,Data!$M14,COLUMNS(Data!$F$1:J13)),"")
B19: =IFERROR(INDEX(Data!$A$2:$E$45,Data!$M15,COLUMNS(Data!$F$1:F14)),"") | C19: =IFERROR(INDEX(Data!$A$2:$E$45,Data!$M15,COLUMNS(Data!$F$1:G14)),"") | D19: =IFERROR(INDEX(Data!$A$2:$E$45,Data!$M15,COLUMNS(Data!$F$1:H14)),"") | E19: =IFERROR(INDEX(Data!$A$2:$E$45,Data!$M15,COLUMNS(Data!$F$1:I14)),"") | F19: =IFERROR(INDEX(Data!$A$2:$E$45,Data!$M15,COLUMNS(Data!$F$1:J14)),"")
B20: =IFERROR(INDEX(Data!$A$2:$E$45,Data!$M16,COLUMNS(Data!$F$1:F15)),"") | C20: =IFERROR(INDEX(Data!$A$2:$E$45,Data!$M16,COLUMNS(Data!$F$1:G15)),"") | D20: =IFERROR(INDEX(Data!$A$2:$E$45,Data!$M16,COLUMNS(Data!$F$1:H15)),"") | E20: =IFERROR(INDEX(Data!$A$2:$E$45,Data!$M16,COLUMNS(Data!$F$1:I15)),"") | F20: =IFERROR(INDEX(Data!$A$2:$E$45,Data!$M16,COLUMNS(Data!$F$1:J15)),"")
B21: =IFERROR(INDEX(Data!$A$2:$E$45,Data!$M17,COLUMNS(Data!$F$1:F16)),"") | C21: =IFERROR(INDEX(Data!$A$2:$E$45,Data!$M17,COLUMNS(Data!$F$1:G16)),"") | D21: =IFERROR(INDEX(Data!$A$2:$E$45,Data!$M17,COLUMNS(Data!$F$1:H16)),"") | E21: =IFERROR(INDEX(Data!$A$2:$E$45,Data!$M17,COLUMNS(Data!$F$1:I16)),"") | F21: =IFERROR(INDEX(Data!$A$2:$E$45,Data!$M17,COLUMNS(Data!$F$1:J16)),"")
B22: =IFERROR(INDEX(Data!$A$2:$E$45,Data!$M18,COLUMNS(Data!$F$1:F17)),"") | C22: =IFERROR(INDEX(Data!$A$2:$E$45,Data!$M18,COLUMNS(Data!$F$1:G17)),"") | D22: =IFERROR(INDEX(Data!$A$2:$E$45,Data!$M18,COLUMNS(Data!$F$1:H17)),"") | E22: =IFERROR(INDEX(Data!$A$2:$E$45,Data!$M18,COLUMNS(Data!$F$1:I17)),"") | F22: =IFERROR(INDEX(Data!$A$2:$E$45,Data!$M18,COLUMNS(Data!$F$1:J17)),"")
B23: =IFERROR(INDEX(Data!$A$2:$E$45,Data!$M19,COLUMNS(Data!$F$1:F18)),"") | C23: =IFERROR(INDEX(Data!$A$2:$E$45,Data!$M19,COLUMNS(Data!$F$1:G18)),"") | D23: =IFERROR(INDEX(Data!$A$2:$E$45,Data!$M19,COLUMNS(Data!$F$1:H18)),"") | E23: =IFERROR(INDEX(Data!$A$2:$E$45,Data!$M19,COLUMNS(Data!$F$1:I18)),"") | F23: =IFERROR(INDEX(Data!$A$2:$E$45,Data!$M19,COLUMNS(Data!$F$1:J18)),"")
B24: =IFERROR(INDEX(Data!$A$2:$E$45,Data!$M20,COLUMNS(Data!$F$1:F19)),"") | C24: =IFERROR(INDEX(Data!$A$2:$E$45,Data!$M20,COLUMNS(Data!$F$1:G19)),"") | D24: =IFERROR(INDEX(Data!$A$2:$E$45,Data!$M20,COLUMNS(Data!$F$1:H19)),"") | E24: =IFERROR(INDEX(Data!$A$2:$E$45,Data!$M20,COLUMNS(Data!$F$1:I19)),"") | F24: =IFERROR(INDEX(Data!$A$2:$E$45,Data!$M20,COLUMNS(Data!$F$1:J19)),"")
B25: =IFERROR(INDEX(Data!$A$2:$E$45,Data!$M21,COLUMNS(Data!$F$1:F20)),"") | C25: =IFERROR(INDEX(Data!$A$2:$E$45,Data!$M21,COLUMNS(Data!$F$1:G20)),"") | D25: =IFERROR(INDEX(Data!$A$2:$E$45,Data!$M21,COLUMNS(Data!$F$1:H20)),"") | E25: =IFERROR(INDEX(Data!$A$2:$E$45,Data!$M21,COLUMNS(Data!$F$1:I20)),"") | F25: =IFERROR(INDEX(Data!$A$2:$E$45,Data!$M21,COLUMNS(Data!$F$1:J20)),"")
... B36: =IFERROR(INDEX(Data!$A$2:$E$45,Data!$M32,COLUMNS(Data!$F$1:F31)),"") | C36: =IFERROR(INDEX(Data!$A$2:$E$45,Data!$M32,COLUMNS(Data!$F$1:G31)),"") | D36: =IFERROR(INDEX(Data!$A$2:$E$45,Data!$M32,COLUMNS(Data!$F$1:H31)),"") | E36: =IFERROR(INDEX(Data!$A$2:$E$45,Data!$M32,COLUMNS(Data!$F$1:I31)),"") | F36: =IFERROR(INDEX(Data!$A$2:$E$45,Data!$M32,COLUMNS(Data!$F$1:J31)),"")

Sheet Data1
A1: Month | B1: Product | C1: Salesperson | D1: Unit Cost | E1: Unit SP | F1: Unit Profit | G1: Count | H1: KPI_1 | I1: Total sales | J1: Total GP
A2: 39814 | B2: Product A | C2: Salesperson 1 | D2: =VLOOKUP(B2,Product_LUP,2,FALSE) -> 20 | E2: =VLOOKUP(B2,Product_LUP,3,FALSE) -> 50 | F2: =E2-D2 -> 30 | G2: 20 | H2: 50 | I2: =G2*E2 -> 1000 | J2: =G2*F2 -> 600
A3: 39814 | B3: Product A | C3: Salesperson 2 | D3: =VLOOKUP(B3,Product_LUP,2,FALSE) -> 20 | E3: =VLOOKUP(B3,Product_LUP,3,FALSE) -> 50 | F3: =E3-D3 -> 30 | G3: 60 | H3: 20 | I3: =G3*E3 -> 3000 | J3: =G3*F3 -> 1800
A4: 39814 | B4: Product A | C4: Salesperson 3 | D4: =VLOOKUP(B4,Product_LUP,2,FALSE) -> 20 | E4: =VLOOKUP(B4,Product_LUP,3,FALSE) -> 50 | F4: =E4-D4 -> 30 | G4: 100 | H4: 60 | I4: =G4*E4 -> 5000 | J4: =G4*F4 -> 3000
A5: 39814 | B5: Product A | C5: Salesperson 4 | D5: =VLOOKUP(B5,Product_LUP,2,FALSE) -> 20 | E5: =VLOOKUP(B5,Product_LUP,3,FALSE) -> 50 | F5: =E5-D5 -> 30 | G5: 80 | H5: 40 | I5: =G5*E5 -> 4000 | J5: =G5*F5 -> 2400
A6: 39814 | B6: Product A | C6: Salesperson 5 | D6: =VLOOKUP(B6,Product_LUP,2,FALSE) -> 20 | E6: =VLOOKUP(B6,Product_LUP,3,FALSE) -> 50 | F6: =E6-D6 -> 30 | G6: 60 | H6: 50 | I6: =G6*E6 -> 3000 | J6: =G6*F6 -> 1800
A7: 39814 | B7: Product B | C7: Salesperson 1 | D7: =VLOOKUP(B7,Product_LUP,2,FALSE) -> 50 | E7: =VLOOKUP(B7,Product_LUP,3,FALSE) -> 80 | F7: =E7-D7 -> 30 | G7: 30 | H7: 60 | I7: =G7*E7 -> 2400 | J7: =G7*F7 -> 900
A8: 39814 | B8: Product B | C8: Salesperson 2 | D8: =VLOOKUP(B8,Product_LUP,2,FALSE) -> 50 | E8: =VLOOKUP(B8,Product_LUP,3,FALSE) -> 80 | F8: =E8-D8 -> 30 | G8: 70 | H8: 80 | I8: =G8*E8 -> 5600 | J8: =G8*F8 -> 2100
A9: 39814 | B9: Product B | C9: Salesperson 3 | D9: =VLOOKUP(B9,Product_LUP,2,FALSE) -> 50 | E9: =VLOOKUP(B9,Product_LUP,3,FALSE) -> 80 | F9: =E9-D9 -> 30 | G9: 70 | H9: 23 | I9: =G9*E9 -> 5600 | J9: =G9*F9 -> 2100
A10: 39814 | B10: Product B | C10: Salesperson 4 | D10: =VLOOKUP(B10,Product_LUP,2,FALSE) -> 50 | E10: =VLOOKUP(B10,Product_LUP,3,FALSE) -> 80 | F10: =E10-D10 -> 30 | G10: 60 | H10: 56 | I10: =G10*E10 -> 4800 | J10: =G10*F10 -> 1800
A11: 39814 | B11: Product B | C11: Salesperson 5 | D11: =VLOOKUP(B11,Product_LUP,2,FALSE) -> 50 | E11: =VLOOKUP(B11,Product_LUP,3,FALSE) -> 80 | F11: =E11-D11 -> 30 | G11: 70 | H11: 98 | I11: =G11*E11 -> 5600 | J11: =G11*F11 -> 2100
A12: 39814 | B12: Product C | C12: Salesperson 1 | D12: =VLOOKUP(B12,Product_LUP,2,FALSE) -> 60 | E12: =VLOOKUP(B12,Product_LUP,3,FALSE) -> 70 | F12: =E12-D12 -> 10 | G12: 50 | H12: 30 | I12: =G12*E12 -> 3500 | J12: =G12*F12 -> 500
A13: 39814 | B13: Product C | C13: Salesperson 2 | D13: =VLOOKUP(B13,Product_LUP,2,FALSE) -> 60 | E13: =VLOOKUP(B13,Product_LUP,3,FALSE) -> 70 | F13: =E13-D13 -> 10 | G13: 80 | H13: 100 | I13: =G13*E13 -> 5600 | J13: =G13*F13 -> 800
... A141: 39995 | B141: Product D | C141: Salesperson 5 | D141: =VLOOKUP(B141,Product_LUP,2,FALSE) -> 10 | E141: =VLOOKUP(B141,Product_LUP,3,FALSE) -> 30 | F141: =E141-D141 -> 20 | G141: 10 | H141: 1 | I141: =G141*E141 -> 300 | J141: =G141*F141 -> 200

Sheet Inputs
A1: Position_Range | C1: Prod_List | E1: SP_List | G1: Period_List | I1: KPI_Name
A2: Top Left | C2: All Product | E2: All Salespeople | G2: YTD | I2: Count | J2: Count of Sale
A3: Middle Left | C3: Product A | E3: Salesperson 1 | G3: 39814 | I3: Total_Sales | J3: Total_Sales
A4: Bottom Left | C4: Product B | E4: Salesperson 2 | G4: 39845 | I4: Total_GP | J4: Total-GP
A5: Top Right | C5: Product C | E5: Salesperson 3 | G5: 39873 | I5: KPI_1 | J5: KPI
A6: Bottom Right | C6: Product D | E6: Salesperson 4 | G6: 39904
A7: Middle Right | E7: Salesperson 5 | G7: 39934
A8: View | G8: 39965
A9: Hide | G9: 39995
G10: 40026
G11: 40057
G12: 40087
G13: 40118
G14: 40148

Sheet Sheet8
B1: Salesperson Analysis
B2: =VLOOKUP($C$21,KPI_Name,2,FALSE)&" "&"For"&" "&C19&"-"&TEXT(C20,"mmm-yy") -> Total-GP For Product C-May-09
B19: Product Group | C19: Product C
B20: Month | C20: 39934
B21: KPI | C21: Total_GP
B23: Salesperson | D23: Product & Period | E23: Product & YTD | F23: All Products & Period | G23: All Products & YTD
B24: Salesperson 1 | C24: =IF(AND($C$19="All Product",$C$20="YTD"),G24,IF(AND($C$19="All Product",$C$20<>"YTD"),F24,IF(AND($C$19<>"All Produt",$C$20="YTD"),E24,D24))) -> 300 | D24: =SUMIFS(INDIRECT($C$21),Sales_Per,B24,Product,$C$19,Period,$C$20) -> 300 | E24: =SUMIFS(INDIRECT($C$21),Sales_Per,B24,Product,$C$19) -> 2980 | F24: =SUMIFS(INDIRECT($C$21),Sales_Per,B24,Period,$C$20) -> 2900 | G24: =SUMIFS(INDIRECT($C$21),Sales_Per,B24) -> 24910 | H24: =G24/$G$30 -> 0.13096052
B25: Salesperson 2 | C25: =IF(AND($C$19="All Product",$C$20="YTD"),G25,IF(AND($C$19="All Product",$C$20<>"YTD"),F25,IF(AND($C$19<>"All Produt",$C$20="YTD"),E25,D25))) -> 900 | D25: =SUMIFS(INDIRECT($C$21),Sales_Per,B25,Product,$C$19,Period,$C$20) -> 900 | E25: =SUMIFS(INDIRECT($C$21),Sales_Per,B25,Product,$C$19) -> 4940 | F25: =SUMIFS(INDIRECT($C$21),Sales_Per,B25,Period,$C$20) -> 6600 | G25: =SUMIFS(INDIRECT($C$21),Sales_Per,B25) -> 40510 | H25: =G25/$G$30 -> 0.21297513
B26: Salesperson 3 | C26: =IF(AND($C$19="All Product",$C$20="YTD"),G26,IF(AND($C$19="All Product",$C$20<>"YTD"),F26,IF(AND($C$19<>"All Produt",$C$20="YTD"),E26,D26))) -> 1300 | D26: =SUMIFS(INDIRECT($C$21),Sales_Per,B26,Product,$C$19,Period,$C$20) -> 1300 | E26: =SUMIFS(INDIRECT($C$21),Sales_Per,B26,Product,$C$19) -> 7610 | F26: =SUMIFS(INDIRECT($C$21),Sales_Per,B26,Period,$C$20) -> 9800 | G26: =SUMIFS(INDIRECT($C$21),Sales_Per,B26) -> 60850 | H26: =G26/$G$30 -> 0.31990957
B27: Salesperson 4 | C27: =IF(AND($C$19="All Product",$C$20="YTD"),G27,IF(AND($C$19="All Product",$C$20<>"YTD"),F27,IF(AND($C$19<>"All Produt",$C$20="YTD"),E27,D27))) -> 650 | D27: =SUMIFS(INDIRECT($C$21),Sales_Per,B27,Product,$C$19,Period,$C$20) -> 650 | E27: =SUMIFS(INDIRECT($C$21),Sales_Per,B27,Product,$C$19) -> 3810 | F27: =SUMIFS(INDIRECT($C$21),Sales_Per,B27,Period,$C$20) -> 5540 | G27: =SUMIFS(INDIRECT($C$21),Sales_Per,B27) -> 41840 | H27: =G27/$G$30 -> 0.2199674
B28: Salesperson 5 | C28: =IF(AND($C$19="All Product",$C$20="YTD"),G28,IF(AND($C$19="All Product",$C$20<>"YTD"),F28,IF(AND($C$19<>"All Produt",$C$20="YTD"),E28,D28))) -> 500 | D28: =SUMIFS(INDIRECT($C$21),Sales_Per,B28,Product,$C$19,Period,$C$20) -> 500 | E28: =SUMIFS(INDIRECT($C$21),Sales_Per,B28,Product,$C$19) -> 3100 | F28: =SUMIFS(INDIRECT($C$21),Sales_Per,B28,Period,$C$20) -> 2000 | G28: =SUMIFS(INDIRECT($C$21),Sales_Per,B28) -> 22100 | H28: =G28/$G$30 -> 0.11618737
B30: Total | C30: =SUM(C24:C28) -> 3650 | D30: =SUM(D24:D28) -> 3650 | E30: =SUM(E24:E28) -> 22440 | F30: =SUM(F24:F28) -> 26840 | G30: =SUM(G24:G28) -> 190210

Sheet Sheet1
C2: Product Range Analysis
C3: =VLOOKUP($C$21,KPI_Name,2,FALSE)&" "&"For"&" "&C19 &"-"&" "& TEXT(C20,"mmm-yy") -> KPI For Salesperson 2- May-09
B19: Salesperson: | C19: Salesperson 2
B20: Month: | C20: 39934
B21: KPI: | C21: KPI_1
B23: Product | D23: Salesperson & Period | E23: Salesperson & YTD | F23: All Salespersons & Period | G23: All Salespersons & YTD
B24: Product A | C24: =IF(AND($C$19="All Salespeople",$C$20="YTD"),G24,IF(AND($C$19="All Salespeople",$C$20<>"YTD"),F24,IF(AND($C$19<>"All Salespeople",$C$20="YTD"),E24,D24))) -> 52 | D24: =SUMIFS(INDIRECT($C$21),Sales_Per,$C$19,Product,B24,Period,$C$20) -> 52 | E24: =SUMIFS(INDIRECT($C$21),Sales_Per,$C$19,Product,B24) -> 267 | F24: =SUMIFS(INDIRECT($C$21),Product,B24,Period,$C$20) -> 261 | G24: =SUMIFS(INDIRECT($C$21),Product,B24) -> 1698
B25: Product B | C25: =IF(AND($C$19="All Salespeople",$C$20="YTD"),G25,IF(AND($C$19="All Salespeople",$C$20<>"YTD"),F25,IF(AND($C$19<>"All Salespeople",$C$20="YTD"),E25,D25))) -> 56 | D25: =SUMIFS(INDIRECT($C$21),Sales_Per,$C$19,Product,B25,Period,$C$20) -> 56 | E25: =SUMIFS(INDIRECT($C$21),Sales_Per,$C$19,Product,B25) -> 414 | F25: =SUMIFS(INDIRECT($C$21),Product,B25,Period,$C$20) -> 278 | G25: =SUMIFS(INDIRECT($C$21),Product,B25) -> 2000
B26: Product C | C26: =IF(AND($C$19="All Salespeople",$C$20="YTD"),G26,IF(AND($C$19="All Salespeople",$C$20<>"YTD"),F26,IF(AND($C$19<>"All Salespeople",$C$20="YTD"),E26,D26))) -> 12 | D26: =SUMIFS(INDIRECT($C$21),Sales_Per,$C$19,Product,B26,Period,$C$20) -> 12 | E26: =SUMIFS(INDIRECT($C$21),Sales_Per,$C$19,Product,B26) -> 362 | F26: =SUMIFS(INDIRECT($C$21),Product,B26,Period,$C$20) -> 199 | G26: =SUMIFS(INDIRECT($C$21),Product,B26) -> 2172
B27: Product D | C27: =IF(AND($C$19="All Salespeople",$C$20="YTD"),G27,IF(AND($C$19="All Salespeople",$C$20<>"YTD"),F27,IF(AND($C$19<>"All Salespeople",$C$20="YTD"),E27,D27))) -> 20 | D27: =SUMIFS(INDIRECT($C$21),Sales_Per,$C$19,Product,B27,Period,$C$20) -> 20 | E27: =SUMIFS(INDIRECT($C$21),Sales_Per,$C$19,Product,B27) -> 402 | F27: =SUMIFS(INDIRECT($C$21),Product,B27,Period,$C$20) -> 116 | G27: =SUMIFS(INDIRECT($C$21),Product,B27) -> 1699
B29: Total | C29: =SUM(C24:C27) -> 140 | D29: =SUM(D24:D27) -> 140 | E29: =SUM(E24:E27) -> 1445 | F29: =SUM(F24:F27) -> 854 | G29: =SUM(G24:G27) -> 7569
